LICENSE
MANIFEST.in
README.rst
setup.py
./shiva/__init__.py
./shiva/admin.py
./shiva/app.py
./shiva/bin.py
./shiva/constants.py
./shiva/converter.py
./shiva/dbtypes.py
./shiva/decorators.py
./shiva/exceptions.py
./shiva/fileserver.py
./shiva/http.py
./shiva/logging.conf
./shiva/media.py
./shiva/mocks.py
./shiva/models.py
./shiva/utils.py
./shiva/auth/__init__.py
./shiva/auth/const.py
./shiva/auth/resource.py
./shiva/config/__init__.py
./shiva/config/project.py
./shiva/indexer/__init__.py
./shiva/indexer/cache.py
./shiva/indexer/lastfm.py
./shiva/indexer/main.py
./shiva/lyrics/__init__.py
./shiva/lyrics/azlyrics.py
./shiva/lyrics/base.py
./shiva/lyrics/letrascanciones.py
./shiva/lyrics/metrolyrics.py
./shiva/resources/__init__.py
./shiva/resources/base.py
./shiva/resources/dynamic.py
./shiva/resources/fields.py
./shiva/resources/static.py
./shiva/resources/upload.py
./tests/__init__.py
./tests/integration/__init__.py
./tests/integration/admin-test.py
./tests/integration/auth-test.py
./tests/integration/indexer-test.py
./tests/integration/resource-albums-test.py
./tests/integration/resource-artists-test.py
./tests/integration/resource-playlists-test.py
./tests/integration/resource-tracks-test.py
./tests/integration/resource-users-test.py
./tests/integration/resource.py
./tests/integration/statuscodes-test.py
./tests/unit/__init__.py
./tests/unit/app-test.py
./tests/unit/byte-range-test.py
./tests/unit/cachemanager-test.py
./tests/unit/config-test.py
./tests/unit/exceptions-test.py
./tests/unit/http-test.py
./tests/unit/indexer-test.py
./tests/unit/lastfm-test.py
./tests/unit/metadata-test.py
./tests/unit/utils.py
shiva/__init__.py
shiva/admin.py
shiva/app.py
shiva/bin.py
shiva/constants.py
shiva/converter.py
shiva/dbtypes.py
shiva/decorators.py
shiva/exceptions.py
shiva/fileserver.py
shiva/http.py
shiva/media.py
shiva/mocks.py
shiva/models.py
shiva/utils.py
shiva.egg-info/PKG-INFO
shiva.egg-info/SOURCES.txt
shiva.egg-info/dependency_links.txt
shiva.egg-info/entry_points.txt
shiva.egg-info/requires.txt
shiva.egg-info/top_level.txt
shiva/auth/__init__.py
shiva/auth/const.py
shiva/auth/resource.py
shiva/config/__init__.py
