Metadata-Version: 1.1
Name: shiva
Version: 0.10.0
Summary: A RESTful API to your music collection
Home-page: https://github.com/tooxie/shiva-server
Author: Alvaro Mouriño
Author-email: alvaro@mourino.net
License: MIT
Download-URL: https://codeload.github.com/tooxie/shiva-server/zip/master
Platform: OS-independent
Platform: Any
Classifier: Development Status :: 3 - Alpha
Classifier: Environment :: Web Environment
Classifier: Intended Audience :: Developers
Classifier: License :: OSI Approved :: MIT License
Classifier: Operating System :: OS Independent
Classifier: Programming Language :: Python :: 2 :: Only
Classifier: Programming Language :: Python :: 2.7
Classifier: Programming Language :: Python
Classifier: Topic :: Communications :: File Sharing
Classifier: Topic :: Internet :: WWW/HTTP :: WSGI :: Server
Classifier: Topic :: Multimedia :: Sound/Audio
Classifier: Topic :: Multimedia
